gloser/__init__.py
gloser/gloser.py
gloser/locale-defaults/af.yaml
gloser/locale-defaults/am.yaml
gloser/locale-defaults/ar.yaml
gloser/locale-defaults/az.yaml
gloser/locale-defaults/be.yaml
gloser/locale-defaults/bg.yaml
gloser/locale-defaults/bn.yaml
gloser/locale-defaults/bs.yaml
gloser/locale-defaults/ca.yaml
gloser/locale-defaults/cs.yaml
gloser/locale-defaults/da.yaml
gloser/locale-defaults/de.yaml
gloser/locale-defaults/dz.yaml
gloser/locale-defaults/el.yaml
gloser/locale-defaults/en.yaml
gloser/locale-defaults/es.yaml
gloser/locale-defaults/et.yaml
gloser/locale-defaults/fa.yaml
gloser/locale-defaults/fi.yaml
gloser/locale-defaults/fr.yaml
gloser/locale-defaults/ha.yaml
gloser/locale-defaults/he.yaml
gloser/locale-defaults/hi.yaml
gloser/locale-defaults/hr.yaml
gloser/locale-defaults/hu.yaml
gloser/locale-defaults/hy.yaml
gloser/locale-defaults/id.yaml
gloser/locale-defaults/ig.yaml
gloser/locale-defaults/is.yaml
gloser/locale-defaults/it.yaml
gloser/locale-defaults/ja.yaml
gloser/locale-defaults/ka.yaml
gloser/locale-defaults/kk.yaml
gloser/locale-defaults/km.yaml
gloser/locale-defaults/ko.yaml
gloser/locale-defaults/ku.yaml
gloser/locale-defaults/ky.yaml
gloser/locale-defaults/lo.yaml
gloser/locale-defaults/lt.yaml
gloser/locale-defaults/lv.yaml
gloser/locale-defaults/mn.yaml
gloser/locale-defaults/ms.yaml
gloser/locale-defaults/my.yaml
gloser/locale-defaults/nb.yaml
gloser/locale-defaults/ne.yaml
gloser/locale-defaults/nl.yaml
gloser/locale-defaults/nn.yaml
gloser/locale-defaults/no.yaml
gloser/locale-defaults/pl.yaml
gloser/locale-defaults/pt.yaml
gloser/locale-defaults/ro.yaml
gloser/locale-defaults/ru.yaml
gloser/locale-defaults/si.yaml
gloser/locale-defaults/sk.yaml
gloser/locale-defaults/sl.yaml
gloser/locale-defaults/sn.yaml
gloser/locale-defaults/so.yaml
gloser/locale-defaults/sq.yaml
gloser/locale-defaults/sr.yaml
gloser/locale-defaults/sv.yaml
gloser/locale-defaults/sw.yaml
gloser/locale-defaults/ta.yaml
gloser/locale-defaults/th.yaml
gloser-1.1.0.dist-info/licenses/LICENSE
gloser-1.1.0.dist-info/METADATA
gloser-1.1.0.dist-info/WHEEL
gloser-1.1.0.dist-info/top_level.txt
gloser-1.1.0.dist-info/RECORD
