Metadata-Version: 2.4
Name: gloser
Version: 1.1.0
Summary: Simple i18n for Python
Author: Are Meisfjord
License-Expression: MIT
Project-URL: Homepage, https://github.com/aremeis/gloser
Project-URL: Repository, https://github.com/aremeis/gloser
Project-URL: Issues, https://github.com/aremeis/gloser/issues
Keywords: i18n,internationalization,localization,translation
Classifier: Development Status :: 3 - Alpha
Classifier: Intended Audience :: Developers
Classifier: Programming Language :: Python :: 3
Classifier: Programming Language :: Python :: 3.8
Classifier: Programming Language :: Python :: 3.9
Classifier: Programming Language :: Python :: 3.10
Classifier: Programming Language :: Python :: 3.11
Classifier: Programming Language :: Python :: 3.12
Classifier: Topic :: Software Development :: Internationalization
Requires-Python: >=3.8
License-File: LICENSE
Requires-Dist: pyyaml>=6.0
Provides-Extra: dev
Requires-Dist: pytest>=7.0; extra == "dev"
Requires-Dist: pytest-cov>=4.0; extra == "dev"
Dynamic: license-file
